[
  {
    "type": "function",
    "inputs": [
      {
        "name": "mutualId",
        "type": "bytes32",
        "baseType": "bytes32",
        "components": null,
        "arrayLength": null,
        "arrayChildren": null
      }
    ],
    "name": "confirmedRival",
    "constant": true,
    "outputs": [
      {
        "name": "",
        "type": "bytes32",
        "baseType": "bytes32",
        "components": null,
        "arrayLength": null,
        "arrayChildren": null
      }
    ],
    "stateMutability": "view",
    "payable": false,
    "gas": null
  }
]