[
  {
    "type": "function",
    "inputs": [
      {
        "name": "_rollup",
        "type": "address",
        "baseType": "address",
        "components": null,
        "arrayLength": null,
        "arrayChildren": null
      }
    ],
    "name": "updateRollupAddress",
    "constant": false,
    "outputs": [],
    "stateMutability": "nonpayable",
    "payable": false,
    "gas": null
  },
  {
    "type": "function",
    "inputs": [
      {
        "name": "",
        "type": "address",
        "baseType": "address",
        "components": null,
        "arrayLength": null,
        "arrayChildren": null
      }
    ],
    "name": "updateRollupAddress",
    "constant": true,
    "outputs": [],
    "stateMutability": "pure",
    "payable": false,
    "gas": null
  }
]