[
  {
    "type": "event",
    "inputs": [
      {
        "name": "batchSequenceNumber",
        "type": "uint256",
        "baseType": "uint256",
        "indexed": true,
        "components": null,
        "arrayLength": null,
        "arrayChildren": null
      },
      {
        "name": "beforeAcc",
        "type": "bytes32",
        "baseType": "bytes32",
        "indexed": true,
        "components": null,
        "arrayLength": null,
        "arrayChildren": null
      },
      {
        "name": "afterAcc",
        "type": "bytes32",
        "baseType": "bytes32",
        "indexed": true,
        "components": null,
        "arrayLength": null,
        "arrayChildren": null
      },
      {
        "name": "delayedAcc",
        "type": "bytes32",
        "baseType": "bytes32",
        "indexed": false,
        "components": null,
        "arrayLength": null,
        "arrayChildren": null
      },
      {
        "name": "afterDelayedMessagesRead",
        "type": "uint256",
        "baseType": "uint256",
        "indexed": false,
        "components": null,
        "arrayLength": null,
        "arrayChildren": null
      },
      {
        "name": "timeBounds",
        "type": "tuple",
        "baseType": "tuple",
        "indexed": false,
        "components": [
          {
            "name": "minTimestamp",
            "type": "uint64",
            "baseType": "uint64",
            "components": null,
            "arrayLength": null,
            "arrayChildren": null
          },
          {
            "name": "maxTimestamp",
            "type": "uint64",
            "baseType": "uint64",
            "components": null,
            "arrayLength": null,
            "arrayChildren": null
          },
          {
            "name": "minBlockNumber",
            "type": "uint64",
            "baseType": "uint64",
            "components": null,
            "arrayLength": null,
            "arrayChildren": null
          },
          {
            "name": "maxBlockNumber",
            "type": "uint64",
            "baseType": "uint64",
            "components": null,
            "arrayLength": null,
            "arrayChildren": null
          }
        ],
        "arrayLength": null,
        "arrayChildren": null
      },
      {
        "name": "dataLocation",
        "type": "uint8",
        "baseType": "uint8",
        "indexed": false,
        "components": null,
        "arrayLength": null,
        "arrayChildren": null
      }
    ],
    "name": "SequencerBatchDelivered",
    "anonymous": false
  }
]